LICENSE.txt
README.md
setup.cfg
setup.py
merge_pdf/__init__.py
merge_pdf/merge.py
merge_pdf.egg-info/PKG-INFO
merge_pdf.egg-info/SOURCES.txt
merge_pdf.egg-info/dependency_links.txt
merge_pdf.egg-info/requires.txt
merge_pdf.egg-info/top_level.txt