Metadata-Version: 2.1
Name: merge-pdf
Version: 1.0.1
Summary: Merge by name, all pdfs in the current folder, or specific list of files, into a single pdf file
Home-page: UNKNOWN
Author: Dari Developer
Author-email: hernandezdarifrancisco@gmail.com
License: MIT
Project-URL: Documentation, https://github.com/DariHernandez/merge_pdf/blob/master/README.md
Project-URL: Funding, https://www.paypal.com/paypalme/FranciscoDari
Project-URL: Source, https://github.com/DariHernandez/merge_pdf
Keywords: pdf,merge,merge pdf,pdf files,manage pdf
Platform: UNKNOWN
Requires-Python: >=3.7
